hub_auth_client/__init__.py
hub_auth_client/exceptions.py
hub_auth_client/validator.py
hub_auth_client/django/__init__.py
hub_auth_client/django/admin.py
hub_auth_client/django/admin_actions.py
hub_auth_client/django/admin_auth.py
hub_auth_client/django/admin_helpers.py
hub_auth_client/django/admin_mixins.py
hub_auth_client/django/admin_views.py
hub_auth_client/django/apps.py
hub_auth_client/django/authentication.py
hub_auth_client/django/config_models.py
hub_auth_client/django/decorators.py
hub_auth_client/django/dynamic_permissions.py
hub_auth_client/django/middleware.py
hub_auth_client/django/models.py
hub_auth_client/django/permissions.py
hub_auth_client/django/rls_middleware.py
hub_auth_client/django/rls_models.py
hub_auth_client/django/management/__init__.py
hub_auth_client/django/management/commands/__init__.py
hub_auth_client/django/management/commands/fetch_azure_roles.py
hub_auth_client/django/management/commands/fetch_azure_scopes.py
hub_auth_client/django/management/commands/init_auth_permissions.py
hub_auth_client/django/management/commands/list_endpoints.py
hub_auth_client/django/management/commands/manage_rls.py
hub_auth_client/django/migrations/0001_initial.py
hub_auth_client/django/migrations/0002_rls_models.py
hub_auth_client/django/migrations/0003_azure_ad_config.py
hub_auth_client/django/migrations/0004_rename_hub_auth_cl_url_pat_idx_hub_auth_cl_url_pat_6a85ac_idx_and_more.py
hub_auth_client/django/migrations/0005_remove_allowed_audiences.py
hub_auth_client/django/migrations/0006_merge_20251210_1139.py
hub_auth_client/django/migrations/__init__.py
hub_auth_client/django/static/admin/css/azure_ad_config.css
hub_auth_client/django/static/admin/css/endpoint_mappings.css
hub_auth_client/django/static/admin/js/azure_ad_config.js
hub_auth_client/django/static/admin/js/discover_endpoints.js
hub_auth_client/django/templates/admin/hub_auth_client/endpointpermission/change_list.html
hub_auth_client-1.0.41.dist-info/licenses/LICENSE
hub_auth_client-1.0.41.dist-info/METADATA
hub_auth_client-1.0.41.dist-info/WHEEL
hub_auth_client-1.0.41.dist-info/top_level.txt
hub_auth_client-1.0.41.dist-info/RECORD
