Metadata-Version: 2.4
Name: hub-auth-client
Version: 1.0.41
Summary: MSAL JWT validation library with Entra ID RBAC support
Home-page: https://github.com/rparrish-5542/hub_auth
Author: rparrish-5542
Author-email: rparrish-5542 <rparrish@wedgwood.org>
License: MIT
Project-URL: Homepage, https://github.com/rparrish-5542/hub_auth
Project-URL: Documentation, https://github.com/rparrish-5542/hub_auth/blob/main/README_PACKAGE.md
Project-URL: Repository, https://github.com/rparrish-5542/hub_auth
Project-URL: Issues, https://github.com/rparrish-5542/hub_auth/issues
Keywords: msal,jwt,azure,entra,authentication,rbac,validation
Classifier: Development Status :: 4 - Beta
Classifier: Intended Audience :: Developers
Classifier: License :: OSI Approved :: MIT License
Classifier: Programming Language :: Python :: 3
Classifier: Framework :: Django
Requires-Python: >=3.8
License-File: LICENSE
Requires-Dist: PyJWT>=2.8.0
Requires-Dist: cryptography>=41.0.0
Requires-Dist: requests>=2.31.0
Provides-Extra: django
Requires-Dist: Django>=4.2; extra == "django"
Provides-Extra: dev
Requires-Dist: pytest>=7.4.0; extra == "dev"
Requires-Dist: pytest-django>=4.5.0; extra == "dev"
Requires-Dist: pytest-cov>=4.1.0; extra == "dev"
Requires-Dist: black>=23.0.0; extra == "dev"
Requires-Dist: flake8>=6.0.0; extra == "dev"
Requires-Dist: mypy>=1.0.0; extra == "dev"
Dynamic: author
Dynamic: home-page
Dynamic: license-file
Dynamic: requires-python
